{
    "provider" : {"type" : "string", "min":1, "max":1},
    "mmsi":{"type" : "int", "min":1, "max":1},
    "datetime" : {"type" : "timestamp", "unit": "utc_unix", "min":1, "max":1},
    "lat" : {"type" : "double", "unit":"degrees", "min":1, "max":1},
    "lon" : {"type" : "double", "unit":"degrees", "min":1, "max":1},
    "sog" : {"type" : "int", "unit" : "knots", "min":1, "max":1},
    "cog": {"type" : "int", "unit" : "degrees", "min":1, "max":1},
    "heading" : {"type" : "int", "unit" : "degrees", "min":1, "max":1},
    "vessel_name": {"type" : "string", "min":0, "max":1},
    "imo": {"type": "string", "min":0, "max":1},
    "callsign": {"type": "string", "min":0, "max":1},
    "vessel_type": {"type": "int", "min":0, "max":1},
    "lenght" : {"type" : "double", "min":0, "max":1},
    "width" : {"type" : "double", "min":0, "max":1},
    "draft" : {"type" : "double", "min":0, "max":1},
    "status" : {"type" : "int", "min":0, "max":1},
    "cargo" : {"type" : "int", "min":0, "max":1},
    "transceiver_class" : {"type" : "string", "min":0, "max":1}
}
